treedir/__init__.py
treedir/cli.py
treedir/core.py
treedir/parser.py
treedir/utils.py
treedir/visualizer.py
treedir_py-0.1.2.dist-info/licenses/LICENSE
treedir_py-0.1.2.dist-info/METADATA
treedir_py-0.1.2.dist-info/WHEEL
treedir_py-0.1.2.dist-info/entry_points.txt
treedir_py-0.1.2.dist-info/top_level.txt
treedir_py-0.1.2.dist-info/RECORD
