Metadata-Version: 2.4
Name: treedir-py
Version: 0.1.2
Summary: A Python library for parsing directory structures from text files and implementing them in target folders
Author-email: Parth Nuwal <parthnuwal7@gmail.com>
Maintainer-email: Parth Nuwal <parthnuwal7@gmail.com>
License-Expression: MIT
Project-URL: Homepage, https://github.com/Parthnuwal7/treedir
Project-URL: Documentation, https://github.com/Parthnuwal7/treedir#readme
Project-URL: Repository, https://github.com/Parthnuwal7/treedir
Project-URL: Bug Tracker, https://github.com/Parthnuwal7/treedir
Keywords: directory,structure,tree,filesystem,automation
Classifier: Development Status :: 5 - Production/Stable
Classifier: Intended Audience :: Developers
Classifier: Operating System :: OS Independent
Classifier: Programming Language :: Python :: 3
Classifier: Programming Language :: Python :: 3.7
Classifier: Programming Language :: Python :: 3.8
Classifier: Programming Language :: Python :: 3.9
Classifier: Programming Language :: Python :: 3.10
Classifier: Programming Language :: Python :: 3.11
Classifier: Programming Language :: Python :: 3.12
Classifier: Topic :: Software Development :: Libraries :: Python Modules
Classifier: Topic :: System :: Filesystems
Classifier: Topic :: Utilities
Requires-Python: >=3.7
License-File: LICENSE
Provides-Extra: dev
Requires-Dist: pytest>=6.0; extra == "dev"
Requires-Dist: pytest-cov>=2.10; extra == "dev"
Requires-Dist: black>=21.0; extra == "dev"
Requires-Dist: flake8>=3.8; extra == "dev"
Requires-Dist: mypy>=0.800; extra == "dev"
Dynamic: license-file
